README.md
setup.py
Queue_Manager.egg-info/PKG-INFO
Queue_Manager.egg-info/SOURCES.txt
Queue_Manager.egg-info/dependency_links.txt
Queue_Manager.egg-info/top_level.txt
queue_manager/__init__.py
queue_manager/base_queue_manager.py
queue_manager/queue_consumer.py
queue_manager/queue_producer.py