Metadata-Version: 2.1
Name: Queue-Manager
Version: 0.0.1
Summary: A library for using queues as both a producer and a consumer
Home-page: https://gitlab.com/riftool/queue-manager
Author: Barad & Riftin & Ori
License: UNKNOWN
Platform: UNKNOWN
Classifier: Programming Language :: Python :: 3
Classifier: License :: OSI Approved :: MIT License
Classifier: Operating System :: OS Independent
Requires-Python: >=3.6
